myeasysql/__init__.py
myeasysql/main.py
myeasySQL-1.1.dist-info/METADATA
myeasySQL-1.1.dist-info/WHEEL
myeasySQL-1.1.dist-info/top_level.txt
myeasySQL-1.1.dist-info/RECORD
