Metadata-Version: 2.1
Name: myeasySQL
Version: 1.1
Requires-Dist: mysql-connector-python
